streaming_wds/__init__.py
streaming_wds/_version.py
streaming_wds/dataloader.py
streaming_wds/dataset.py
streaming_wds/decoders.py
streaming_wds/utils.py
streaming_wds/core/__init__.py
streaming_wds/core/cache.py
streaming_wds/core/downloader.py
streaming_wds/core/extractor.py
streaming_wds/core/index.py
streaming_wds/core/sharder.py
streaming_wds/core/types.py
streaming_wds-0.1.28.dist-info/LICENSE
streaming_wds-0.1.28.dist-info/METADATA
streaming_wds-0.1.28.dist-info/WHEEL
streaming_wds-0.1.28.dist-info/top_level.txt
streaming_wds-0.1.28.dist-info/RECORD
