Metadata-Version: 2.1
Name: streaming-wds
Version: 0.1.28
Summary: Iterable Streaming Webdataset for PyTorch from boto3 compliant storage
Author-email: Tony Francis <tony@dream3d.com>
License: MIT
Project-URL: Homepage, https://github.com/dream3d-ai/streaming-wds
Project-URL: Bug Tracker, https://github.com/dream3d-ai/streaming-wds/issues
Keywords: pytorch,webdataset,streaming,iterable,torch
Classifier: Programming Language :: Python :: 3
Classifier: License :: OSI Approved :: MIT License
Classifier: Operating System :: OS Independent
Requires-Python: >=3.7
License-File: LICENSE
Requires-Dist: psutil
Requires-Dist: pyarrow
Requires-Dist: boto3
Requires-Dist: torch
Requires-Dist: tensordict
Requires-Dist: tenacity
Requires-Dist: tqdm
